{
  "schema_version": 1,
  "registry_id": "qianlima-enterprise-mcp-example",
  "default_action": "deny",
  "servers": [
    {
      "server_id": "example-readonly-server",
      "enabled": false,
      "owner_id": "system-owner-ref",
      "vendor": "vendor-ref",
      "version": "0.0.0-unverified",
      "category": "database_and_bi",
      "transport": "stdio_or_approved_http",
      "endpoint_ref": "endpoint-reference-only",
      "credential_ref": "credential-reference-only",
      "network_zone": "zone_2_internal",
      "data_classifications": ["internal_sanitized"],
      "tool_manifest_hash": "sha256:replace-after-contract-test",
      "allowed_tools": [],
      "operation_classes": ["read_selected", "analyze"],
      "rate_limit": {"requests_per_minute": 0},
      "timeout_ms": 30000,
      "cost_model": "unknown_until_rate_card",
      "health_status": "unverified",
      "last_contract_test_at": null,
      "trust_level": "T0",
      "write_enabled": false,
      "direct_agent_access": false
    }
  ]
}
